setup.py
django_dropbox/__init__.py
django_dropbox/models.py
django_dropbox/settings.py
django_dropbox/storage.py
django_dropbox/tests.py
django_dropbox/views.py
django_dropbox.egg-info/PKG-INFO
django_dropbox.egg-info/SOURCES.txt
django_dropbox.egg-info/dependency_links.txt
django_dropbox.egg-info/requires.txt
django_dropbox.egg-info/top_level.txt
django_dropbox/management/__init__.py
django_dropbox/management/commands/__init__.py
django_dropbox/management/commands/get_dropbox_token.py