Metadata-Version: 1.0
Name: django-dropbox
Version: 0.0.1
Summary: A Django App that contains a Django Storage which uses Dropbox.
Home-page: https://github.com/andres-torres-marroquin/django-dropbox
Author: Andres Torres Marroquin
Author-email: andres.torres.marroquin@gmail.com
License: UNKNOWN
Platform: UNKNOWN
